setup.py
django_riemann.egg-info/PKG-INFO
django_riemann.egg-info/SOURCES.txt
django_riemann.egg-info/dependency_links.txt
django_riemann.egg-info/requires.txt
django_riemann.egg-info/top_level.txt
riemann/__init__.py
riemann/handler.py