Metadata-Version: 1.0
Name: django-riemann
Version: 0.0.1
Summary: Send logging data to Riemann
Home-page: https://github.com/honza/django-riemann
Author: Honza Pokorny
Author-email: me@honza.ca
License: UNKNOWN
Platform: UNKNOWN
